MANIFEST.in
README.md
requirements.txt
setup.cfg
setup.py
pynetlib/__init__.py
pynetlib/device.py
pynetlib/exceptions.py
pynetlib/namespace.py
pynetlib/route.py
pynetlib/unification.py
pynetlib/utils.py
pynetlib.egg-info/PKG-INFO
pynetlib.egg-info/SOURCES.txt
pynetlib.egg-info/dependency_links.txt
pynetlib.egg-info/not-zip-safe
pynetlib.egg-info/requires.txt
pynetlib.egg-info/top_level.txt
pynetlib/tests/__init__.py
pynetlib/tests/test_device.py
pynetlib/tests/test_namespace.py
pynetlib/tests/test_route.py
pynetlib/tests/test_unification.py
pynetlib/tests/test_utils.py