Metadata-Version: 1.0
Name: pynetlib
Version: 0.3.0
Summary: Python net library
Home-page: https://github.com/migibert/pynetlib
Author: Mikael Gibert
Author-email: mikael.gibert@gmail.com
License: MIT
Platform: UNKNOWN
